neuromorpholib/__init__.py
neuromorpholib/neuromorpho/__init__.py
neuromorpholib/swc/__init__.py
neuromorpholib-0.1.0.dist-info/METADATA
neuromorpholib-0.1.0.dist-info/RECORD
neuromorpholib-0.1.0.dist-info/WHEEL
neuromorpholib-0.1.0.dist-info/top_level.txt
