Metadata-Version: 2.1
Name: neuromorpholib
Version: 0.1.0
Summary: Library for manipulating neuromorpho resources.
Home-page: UNKNOWN
Author: Jordan Matelsky
Author-email: jordan@matelsky.com
License: Apache 2.0
Download-URL: https://github.com/j6k4m8/neuromorpholib/tarball/0.1.0
Keywords: neuron,morphology,neuroscience,graph
Platform: UNKNOWN
Classifier: Development Status :: 4 - Beta
Classifier: Intended Audience :: Developers
Classifier: Programming Language :: Python :: 3.4
Classifier: Programming Language :: Python :: 3.5
